scripts/__init__.py
scripts/load.py
scripts/pre_process.py
scripts/preprocess.py
scripts/scraper.py
scripts/serve.py
scripts/test.py
scripts/train.py
scripts/data/germany_all.csv
scripts/data/preprocessed_data.csv
tests/__init__.py
tests/preprocess_test.py
tests/scraper_test.py
BundesligaPredictor-0.0.4.dist-info/METADATA
BundesligaPredictor-0.0.4.dist-info/WHEEL
BundesligaPredictor-0.0.4.dist-info/top_level.txt
BundesligaPredictor-0.0.4.dist-info/RECORD
