Metadata-Version: 2.1
Name: BundesligaPredictor
Version: 0.0.4
Requires-Dist: pandas
Requires-Dist: numpy
Requires-Dist: scikit-learn
Requires-Dist: flask
Requires-Dist: bs4
Requires-Dist: requests
Requires-Dist: hyperopt
